setup.py
nkust_ucl/__init__.py
nkust_ucl.egg-info/PKG-INFO
nkust_ucl.egg-info/SOURCES.txt
nkust_ucl.egg-info/dependency_links.txt
nkust_ucl.egg-info/top_level.txt