Metadata-Version: 2.1
Name: nkust-ucl
Version: 0.1.0
Summary: A pip package
Home-page: UNKNOWN
Author: a9931543
License: MIT
Platform: UNKNOWN
Classifier: Programming Language :: Python
Classifier: Programming Language :: Python :: 3.6
